blackbox/__init__.py
blackbox/__main__.py
blackbox/collector.py
blackbox/crash.py
blackbox/filters.py
blackbox/formatter.py
blackbox/tracer.py
blackbox/instruments/__init__.py
blackbox/instruments/audit.py
blackbox/instruments/database.py
blackbox/instruments/environment.py
blackbox/instruments/http.py
blackbox/instruments/memory.py
blackbox/instruments/resources.py
blackbox/instruments/timing.py
jaymd96_blackbox-0.2.0.dist-info/METADATA
jaymd96_blackbox-0.2.0.dist-info/WHEEL
jaymd96_blackbox-0.2.0.dist-info/entry_points.txt
jaymd96_blackbox-0.2.0.dist-info/RECORD
