Metadata-Version: 2.4
Name: jaymd96-blackbox
Version: 0.2.0
Summary: LLM-friendly Python debugger with structured, readable output
Project-URL: Homepage, https://github.com/jaymd96/blackbox
Project-URL: Repository, https://github.com/jaymd96/blackbox
Author-email: James <james@example.com>
License-Expression: MIT
Keywords: crash-handler,debugging,developer-tools,execution-trace,llm,observability,traceback
Classifier: Development Status :: 3 - Alpha
Classifier: Intended Audience :: Developers
Classifier: License :: OSI Approved :: MIT License
Classifier: Operating System :: OS Independent
Classifier: Programming Language :: Python :: 3
Classifier: Programming Language :: Python :: 3.10
Classifier: Programming Language :: Python :: 3.11
Classifier: Programming Language :: Python :: 3.12
Classifier: Programming Language :: Python :: 3.13
Classifier: Topic :: Software Development :: Debuggers
Classifier: Topic :: Software Development :: Testing
Requires-Python: >=3.10
Provides-Extra: dev
Requires-Dist: psutil>=5.9; extra == 'dev'
Requires-Dist: pytest-cov>=4.0; extra == 'dev'
Requires-Dist: pytest>=7.0; extra == 'dev'
Requires-Dist: wrapt>=1.15; extra == 'dev'
Provides-Extra: full
Requires-Dist: psutil>=5.9; extra == 'full'
Requires-Dist: wrapt>=1.15; extra == 'full'
